mixinforge/__init__.py
mixinforge/_version_info.py
mixinforge/py.typed
mixinforge/command_line_tools/__init__.py
mixinforge/command_line_tools/_cli_entry_points.py
mixinforge/command_line_tools/basic_file_utils.py
mixinforge/command_line_tools/project_analyzer.py
mixinforge/context_managers/__init__.py
mixinforge/context_managers/output_capturer.py
mixinforge/context_managers/output_suppressor.py
mixinforge/mixins_and_metaclasses/__init__.py
mixinforge/mixins_and_metaclasses/cacheable_properties_mixin.py
mixinforge/mixins_and_metaclasses/guarded_init_metaclass.py
mixinforge/mixins_and_metaclasses/immutable_mixin.py
mixinforge/mixins_and_metaclasses/immutable_parameterizable_mixin.py
mixinforge/mixins_and_metaclasses/not_picklable_mixin.py
mixinforge/mixins_and_metaclasses/parameterizable_mixin.py
mixinforge/mixins_and_metaclasses/single_thread_enforcer_mixin.py
mixinforge/mixins_and_metaclasses/singleton_mixin.py
mixinforge/utility_functions/__init__.py
mixinforge/utility_functions/atomics_detector.py
mixinforge/utility_functions/dict_sorter.py
mixinforge/utility_functions/json_processor.py
mixinforge/utility_functions/nested_collections_inspector.py
mixinforge/utility_functions/nested_collections_transformer.py
mixinforge/utility_functions/notebook_checker.py
mixinforge/utility_functions/package_manager.py
mixinforge-0.238.0.dist-info/METADATA
mixinforge-0.238.0.dist-info/WHEEL
mixinforge-0.238.0.dist-info/entry_points.txt
mixinforge-0.238.0.dist-info/licenses/LICENSE
mixinforge-0.238.0.dist-info/RECORD
