Metadata-Version: 2.4
Name: mixinforge
Version: 0.238.0
Summary: A collection of Python mixins, metaclasses, context managers, utility functions, and CLI tools for building robust, configurable classes.
Project-URL: Home, https://github.com/pythagoras-dev/mixinforge
Project-URL: Docs, https://mixinforge.readthedocs.io/
Author-email: "Vlad (Volodymyr) Pavlov" <vlpavlov@ieee.org>
License: MIT
License-File: LICENSE
Keywords: cached-property,caching,json,metaclass,mixins,parameters,serialization,singleton,thread-safety,utilities
Classifier: Development Status :: 4 - Beta
Classifier: Intended Audience :: Developers
Classifier: Intended Audience :: Science/Research
Classifier: License :: OSI Approved :: MIT License
Classifier: Operating System :: OS Independent
Classifier: Programming Language :: Python
Classifier: Programming Language :: Python :: 3
Classifier: Programming Language :: Python :: 3.11
Classifier: Programming Language :: Python :: 3.12
Classifier: Programming Language :: Python :: 3.13
Classifier: Programming Language :: Python :: 3.14
Classifier: Topic :: Software Development :: Libraries
Classifier: Topic :: Software Development :: Libraries :: Python Modules
Classifier: Typing :: Typed
Requires-Python: >=3.11
Requires-Dist: tabulate
Requires-Dist: uv
Provides-Extra: dev
Requires-Dist: coverage; extra == 'dev'
Requires-Dist: myst-parser; extra == 'dev'
Requires-Dist: pydata-sphinx-theme; extra == 'dev'
Requires-Dist: pytest; extra == 'dev'
Requires-Dist: ruff; extra == 'dev'
Requires-Dist: sphinx; extra == 'dev'
Requires-Dist: sphinx-autodoc-typehints; extra == 'dev'
Requires-Dist: sphinx-copybutton; extra == 'dev'
Requires-Dist: uv-publish; extra == 'dev'
Provides-Extra: docs
Requires-Dist: myst-parser; extra == 'docs'
Requires-Dist: pydata-sphinx-theme; extra == 'docs'
Requires-Dist: sphinx; extra == 'docs'
Requires-Dist: sphinx-autodoc-typehints; extra == 'docs'
Requires-Dist: sphinx-copybutton; extra == 'docs'
